krag/__init__.py
krag/document.py
krag/evaluators.py
krag/retrievers.py
krag/tokenizers.py
krag/utils.py
krag-0.0.32.dist-info/METADATA
krag-0.0.32.dist-info/WHEEL
krag-0.0.32.dist-info/RECORD
