Metadata-Version: 2.3
Name: krag
Version: 0.0.32
Summary: A Python package for RAG performance evaluation
Keywords: RAG,Recall,MRR,mAP,NDCG
Author: Pandas-Studio
Author-email: ontofinance@gmail.com
Requires-Python: >=3.10,<3.13
Classifier: Programming Language :: Python :: 3
Classifier: Programming Language :: Python :: 3.10
Classifier: Programming Language :: Python :: 3.11
Classifier: Programming Language :: Python :: 3.12
Requires-Dist: cython (>=3.0.11,<4.0.0)
Requires-Dist: kiwipiepy (>=0.18.0,<0.19.0)
Requires-Dist: korouge-score (>=0.1.4,<0.2.0)
Requires-Dist: langchain (>=0.3.1,<0.4.0)
Requires-Dist: langchain-community (>=0.3.2,<0.4.0)
Requires-Dist: langchain-huggingface (>=0.3.0,<0.4.0)
Requires-Dist: langchain-ollama (>=0.3.3,<0.4.0)
Requires-Dist: langchain-openai (>=0.3.2,<0.4.0)
Requires-Dist: rank-bm25 (>=0.2.2,<0.3.0)
Requires-Dist: scikit-learn (>=1.7.0,<2.0.0)
Requires-Dist: seaborn (>=0.13.2,<0.14.0)
